pytest_tui/__init__.py
pytest_tui/__main__.py
pytest_tui/_tree_control.py
pytest_tui/data.py
pytest_tui/debug_context.py
pytest_tui/debug_html_logger.py
pytest_tui/foldable_loggers.py
pytest_tui/html_gen.py
pytest_tui/html_gen_new_regex_try.py
pytest_tui/nice_gui.py.py
pytest_tui/nonprintable_​​characters.md
pytest_tui/nonprintable_​​characters.txt
pytest_tui/plugin.py
pytest_tui/regex_test.py.py
pytest_tui/tree_control.py
pytest_tui/tui_gen.py
pytest_tui/tui_logger.py
pytest_tui/utils.py
pytest_tui/log_experiments/debug_context.py
pytest_tui/log_experiments/debug_html_logger.py
pytest_tui/log_experiments/foldable_loggers.py
pytest_tui/log_experiments/test_debug_logger_html.py
pytest_tui/log_experiments/test_me.py
pytest_tui/log_experiments/tui_logger.py
pytest_tui/resources/scripts.js
pytest_tui/resources/styles.css
pytest_tui/stuff/__main__.py
pytest_tui/stuff/devnotes.md
pytest_tui/stuff/nonprintable_​​characters.md
pytest_tui/stuff/nonprintable_​​characters.txt
pytest_tui/stuff/tui_regexes_npc.txt
recordings/__init__.py
recordings/new_recording_rec.py
pytest_tui-2.1.0.dist-info/LICENSE
pytest_tui-2.1.0.dist-info/METADATA
pytest_tui-2.1.0.dist-info/WHEEL
pytest_tui-2.1.0.dist-info/entry_points.txt
pytest_tui-2.1.0.dist-info/top_level.txt
pytest_tui-2.1.0.dist-info/RECORD
