Metadata-Version: 2.1
Name: pytest-tui
Version: 2.1.0
Summary: Text User Interface (TUI) and HTML report for Pytest test runs
Home-page: https://github.com/jeffwright13/pytest-tui
Author: Jeff Wright
Author-email: jeff.washcloth@gmail.com
License: MIT
Keywords: pytest pytest-plugin testing tui textual html
Classifier: Framework :: Pytest
Classifier: Development Status :: 4 - Beta
Classifier: Intended Audience :: Developers
Classifier: Topic :: Software Development :: Testing
Classifier: Programming Language :: Python :: 3.8
Classifier: Programming Language :: Python :: 3.9
Classifier: Operating System :: OS Independent
Classifier: License :: OSI Approved :: MIT License
Requires-Python: >=3.8
License-File: LICENSE
Requires-Dist: ansi2html ==1.8.0
Requires-Dist: faker ==18.3.1
Requires-Dist: json2table ==1.1.5
Requires-Dist: pytest-metadata ==2.0.4
Requires-Dist: single-source ==0.3.0
Requires-Dist: strip-ansi ==0.1.1
Requires-Dist: textual ==0.1.18
